papertronics_sdk/__init__.py
papertronics_sdk/lab/__init__.py
papertronics_sdk/lab/admin_client.py
papertronics_sdk/lab/user_client.py
papertronics_sdk/lab/exceptions/__init__.py
papertronics_sdk/lab/exceptions/status_exception.py
papertronics_sdk/lab/models/__init__.py
papertronics_sdk/lab/models/admin_cloud_models.py
papertronics_sdk/lab/models/cloud_models.py
papertronics_sdk/lab/models/config.py
papertronics_sdk/lab/models/database.py
papertronics_sdk/lab/models/generic.py
papertronics_sdk/lab/models/station_protocol.py
papertronics_sdk-0.0.45.dist-info/LICENSE
papertronics_sdk-0.0.45.dist-info/METADATA
papertronics_sdk-0.0.45.dist-info/WHEEL
papertronics_sdk-0.0.45.dist-info/top_level.txt
papertronics_sdk-0.0.45.dist-info/zip-safe
papertronics_sdk-0.0.45.dist-info/RECORD
