Metadata-Version: 2.1
Name: papertronics-sdk
Version: 0.0.45
Summary: A collection of pydantic models and shared utility functions for SG Papertronics projects
Home-page: https://github.com/SG-Papertronics/shared
Author: Job Heersink
Author-email: j.g.heersink@sgpapertronics.com
License: private
Keywords: beer-o-meter,lab-app,setuptools
Classifier: Programming Language :: Python :: 3
License-File: LICENSE
Requires-Dist: pydantic >=1.10.6
Requires-Dist: httpx >=0.24.1
